changedetection_io-0.52.9.data/scripts/changedetection.py
changedetection_io-0.52.9.dist-info/licenses/LICENSE
changedetectionio/__init__.py
changedetectionio/async_update_worker.py
changedetectionio/auth_decorator.py
changedetectionio/custom_queue.py
changedetectionio/favicon_utils.py
changedetectionio/flask_app.py
changedetectionio/forms.py
changedetectionio/gc_cleanup.py
changedetectionio/html_tools.py
changedetectionio/is_safe_url.py
changedetectionio/languages.py
changedetectionio/notification_service.py
changedetectionio/pluggy_interface.py
changedetectionio/queue_handlers.py
changedetectionio/queuedWatchMetaData.py
changedetectionio/rss_tools.py
changedetectionio/store.py
changedetectionio/strtobool.py
changedetectionio/time_handler.py
changedetectionio/validate_url.py
changedetectionio/worker_handler.py
changedetectionio/api/Import.py
changedetectionio/api/Notifications.py
changedetectionio/api/Search.py
changedetectionio/api/SystemInfo.py
changedetectionio/api/Tags.py
changedetectionio/api/Watch.py
changedetectionio/api/__init__.py
changedetectionio/api/api_schema.py
changedetectionio/api/auth.py
changedetectionio/blueprint/__init__.py
changedetectionio/blueprint/backups/__init__.py
changedetectionio/blueprint/backups/templates/overview.html
changedetectionio/blueprint/browser_steps/TODO.txt
changedetectionio/blueprint/browser_steps/__init__.py
changedetectionio/blueprint/browser_steps/browser_steps.py
changedetectionio/blueprint/check_proxies/__init__.py
changedetectionio/blueprint/imports/__init__.py
changedetectionio/blueprint/imports/importer.py
changedetectionio/blueprint/imports/templates/import.html
changedetectionio/blueprint/price_data_follower/__init__.py
changedetectionio/blueprint/rss/__init__.py
changedetectionio/blueprint/rss/_util.py
changedetectionio/blueprint/rss/blueprint.py
changedetectionio/blueprint/rss/main_feed.py
changedetectionio/blueprint/rss/single_watch.py
changedetectionio/blueprint/rss/tag.py
changedetectionio/blueprint/settings/__init__.py
changedetection_io-0.52.9.dist-info/METADATA
changedetection_io-0.52.9.dist-info/WHEEL
changedetection_io-0.52.9.dist-info/entry_points.txt
changedetection_io-0.52.9.dist-info/top_level.txt
changedetection_io-0.52.9.dist-info/zip-safe
changedetection_io-0.52.9.dist-info/RECORD
