Metadata-Version: 2.4
Name: changedetection.io
Version: 0.52.9
Summary: Website change detection and monitoring service, detect changes to web pages and send alerts/notifications.
Home-page: https://changedetection.io
Author: dgtlmoon
License: Apache License 2.0
Keywords: website change monitor for changes notification change detection alerts tracking website tracker change alert website and monitoring
Classifier: Intended Audience :: Customer Service
Classifier: Intended Audience :: Developers
Classifier: Intended Audience :: Education
Classifier: Intended Audience :: End Users/Desktop
Classifier: Intended Audience :: Financial and Insurance Industry
Classifier: Intended Audience :: Healthcare Industry
Classifier: Intended Audience :: Information Technology
Classifier: Intended Audience :: Legal Industry
Classifier: Intended Audience :: Manufacturing
Classifier: Intended Audience :: Other Audience
Classifier: Intended Audience :: Religion
Classifier: Intended Audience :: Science/Research
Classifier: Intended Audience :: System Administrators
Classifier: Intended Audience :: Telecommunications Industry
Classifier: Topic :: Education
Classifier: Topic :: Internet
Classifier: Topic :: Internet :: WWW/HTTP :: Indexing/Search
Classifier: Topic :: Internet :: WWW/HTTP :: Site Management
Classifier: Topic :: Internet :: WWW/HTTP :: Site Management :: Link Checking
Classifier: Topic :: Internet :: WWW/HTTP :: Browsers
Classifier: Topic :: Internet :: WWW/HTTP :: Dynamic Content
Classifier: Topic :: Office/Business
Classifier: Topic :: Other/Nonlisted Topic
Classifier: Topic :: Scientific/Engineering :: Information Analysis
Classifier: Topic :: Text Processing :: Markup :: HTML
Classifier: Topic :: Utilities
Requires-Python: >= 3.10
License-File: LICENSE
Requires-Dist: feedgen~=1.0
Requires-Dist: feedparser~=6.0
Requires-Dist: flask-compress
Requires-Dist: flask-login>=0.6.3
Requires-Dist: flask-paginate
Requires-Dist: flask_expects_json~=1.7
Requires-Dist: flask_restful
Requires-Dist: flask_cors
Requires-Dist: janus
Requires-Dist: flask_wtf~=1.2
Requires-Dist: flask~=3.1
Requires-Dist: flask-socketio~=5.6.0
Requires-Dist: python-socketio~=5.16.0
Requires-Dist: python-engineio~=4.13.0
Requires-Dist: inscriptis~=2.2
Requires-Dist: pytz
Requires-Dist: timeago~=1.0
Requires-Dist: validators~=0.35
Requires-Dist: brotli~=1.2
Requires-Dist: requests[socks]
Requires-Dist: requests-file
Requires-Dist: chardet>2.3.0
Requires-Dist: wtforms~=3.2
Requires-Dist: jsonpath-ng~=1.7.0
Requires-Dist: orjson~=3.11
Requires-Dist: apprise==1.9.6
Requires-Dist: diff_match_patch
Requires-Dist: linkify-it-py
Requires-Dist: cryptography==46.0.3
Requires-Dist: paho-mqtt!=2.0.*
Requires-Dist: beautifulsoup4<=4.14.3,>=4.0.0
Requires-Dist: lxml!=5.2.0,!=5.2.1,<7,>=4.8.0
Requires-Dist: elementpath==5.1.0
Requires-Dist: selenium~=4.31.0
Requires-Dist: jinja2~=3.1
Requires-Dist: arrow
Requires-Dist: openpyxl
Requires-Dist: jq~=1.3; python_version >= "3.8" and sys_platform == "darwin"
Requires-Dist: jq~=1.3; python_version >= "3.8" and sys_platform == "linux"
Requires-Dist: pyppeteer-ng==2.0.0rc12
Requires-Dist: pyppeteerstealth>=0.0.4
Requires-Dist: pytest~=9.0
Requires-Dist: pytest-flask~=1.3
Requires-Dist: pytest-mock~=3.15
Requires-Dist: jsonschema~=4.26
Requires-Dist: openapi-core[flask]>=0.19.0
Requires-Dist: loguru
Requires-Dist: extruct
Requires-Dist: babel
Requires-Dist: Flask-Babel>=4.0.0
Requires-Dist: levenshtein
Requires-Dist: greenlet>=3.0.3
Requires-Dist: gevent
Requires-Dist: referencing==0.35.1
Requires-Dist: panzi-json-logic
Requires-Dist: price-parser
Requires-Dist: puremagic
Requires-Dist: tzdata
Requires-Dist: pluggy~=1.6
Requires-Dist: psutil==7.2.1
Requires-Dist: ruff>=0.11.2
Requires-Dist: pre_commit>=4.2.0
Requires-Dist: blinker
Requires-Dist: pytest-xdist
Dynamic: author
Dynamic: classifier
Dynamic: description
Dynamic: description-content-type
Dynamic: home-page
Dynamic: keywords
Dynamic: license
Dynamic: license-file
Dynamic: requires-dist
Dynamic: requires-python
Dynamic: summary
